{
    "Average Volume": "2,334,013",
    "Description": "First Solar, Inc., a solar technology company, provides photovoltaic (PV) solar energy solutions in the United States, France, Japan, Chile, and internationally. The company manufactures and sells PV solar modules with a thin film semiconductor technology that provides a lower-carbon alternative to conventional crystalline silicon PV solar modules. It designs, manufactures, and sells cadmium telluride solar modules that converts sunlight into electricity. The company's residual business operations include project development activities, operations and maintenance services, and the sale of PV solar power systems to third-party customers. It serves developers and operators of systems, utilities, independent power producers, commercial and industrial companies, and other system owners. The company was formerly known as First Solar Holdings, Inc. and changed its name to First Solar, Inc. in 2006. First Solar, Inc. was founded in 1999 and is headquartered in Tempe, Arizona.",
    "Dividend Ex-Date": "N/A",
    "EPS": "7.74",
    "Forward Dividend": "N/A (N/A)",
    "Industry": "Solar",
    "Last Updated": "2024-03-01 08:05",
    "Market Cap": "16.443B",
    "Next Earnings Date": "Apr 25, 2024 - Apr 29, 2024",
    "PE Ratio": "19.88",
    "Sector": "Technology",
    "Stock Type": "Company",
    "Symbol": "FSLR",
    "Website": "https://www.firstsolar.com",
    "Yahoo Chart URL": "https://finance.yahoo.com/quote/FSLR/chart?p=FSLR",
    "Yahoo Options URL": "https://finance.yahoo.com/quote/FSLR/options?p=FSLR",
    "Yahoo Summary URL": "https://finance.yahoo.com/quote/FSLR?p=FSLR",
    "Year Range": "129.22 - 232.00"
}